{
  "$schema": "https://developer.microsoft.com/json-schemas/fabric/item/report/definition/visualContainer/2.1.0/schema.json",
  "name": "a64d3c0359d769fea158",
  "position": {
    "x": 832,
    "y": 656,
    "z": 9000,
    "height": 120,
    "width": 440,
    "tabOrder": 9000
  },
  "visual": {
    "visualType": "treemap",
    "query": {
      "queryState": {
        "Details": {
          "projections": [
            {
              "field": {
                "Column": {
                  "Expression": {
                    "SourceRef": {
                      "Entity": "Tiendas"
                    }
                  },
                  "Property": "BV_PAIS"
                }
              },
              "queryRef": "Tiendas.BV_PAIS"
            }
          ]
        },
        "Group": {
          "projections": [
            {
              "field": {
                "Column": {
                  "Expression": {
                    "SourceRef": {
                      "Entity": "Tiendas"
                    }
                  },
                  "Property": "FORMATO_CANAL"
                }
              },
              "queryRef": "Tiendas.FORMATO_CANAL",
              "active": true
            }
          ]
        },
        "Values": {
          "projections": [
            {
              "field": {
                "Measure": {
                  "Expression": {
                    "SourceRef": {
                      "Entity": "Métricas"
                    }
                  },
                  "Property": "DPT"
                }
              },
              "queryRef": "Métricas.DPT"
            }
          ]
        }
      }
    },
    "objects": {
      "legend": [
        {
          "properties": {}
        }
      ],
      "labels": [
        {
          "properties": {
            "show": {
              "expr": {
                "Literal": {
                  "Value": "true"
                }
              }
            }
          }
        }
      ]
    },
    "visualContainerObjects": {
      "title": [
        {
          "properties": {
            "titleWrap": {
              "expr": {
                "Literal": {
                  "Value": "true"
                }
              }
            },
            "fontColor": {
              "solid": {
                "color": {
                  "expr": {
                    "ThemeDataColor": {
                      "ColorId": 0,
                      "Percent": -0.6
                    }
                  }
                }
              }
            },
            "alignment": {
              "expr": {
                "Literal": {
                  "Value": "'center'"
                }
              }
            },
            "fontSize": {
              "expr": {
                "Literal": {
                  "Value": "12D"
                }
              }
            },
            "bold": {
              "expr": {
                "Literal": {
                  "Value": "true"
                }
              }
            },
            "show": {
              "expr": {
                "Literal": {
                  "Value": "false"
                }
              }
            }
          }
        }
      ],
      "background": [
        {
          "properties": {
            "show": {
              "expr": {
                "Literal": {
                  "Value": "true"
                }
              }
            },
            "transparency": {
              "expr": {
                "Literal": {
                  "Value": "0D"
                }
              }
            }
          }
        }
      ]
    },
    "drillFilterOtherVisuals": true
  }
}